pyNLLoc/GetAngles.cpp
pyNLLoc/GridLib.c
pyNLLoc/Scat2Angle.py
pyNLLoc/XYZ2Angle.py
pyNLLoc/__core__.py
pyNLLoc/__init__.py
pyNLLoc/make_angles.sh
pyNLLoc/NLLoc_code/CHANGE_NOTES.txt
pyNLLoc/NLLoc_code/GridLib.c
pyNLLoc/NLLoc_code/GridLib.h
pyNLLoc/NLLoc_code/README.txt
pyNLLoc/NLLoc_code/geo.c
pyNLLoc/NLLoc_code/geo.h
pyNLLoc/NLLoc_code/geo.o
pyNLLoc/NLLoc_code/map_project.c
pyNLLoc/NLLoc_code/map_project.h
pyNLLoc/NLLoc_code/map_project.o
pyNLLoc/NLLoc_code/util.c
pyNLLoc/NLLoc_code/util.h
pyNLLoc/NLLoc_code/util.o
pyNLLoc/NLLoc_code/alomax_matrix/alomax_matrix.c
pyNLLoc/NLLoc_code/alomax_matrix/alomax_matrix.h
pyNLLoc/NLLoc_code/alomax_matrix/alomax_matrix.o
pyNLLoc/NLLoc_code/alomax_matrix/alomax_matrix_svd.c
pyNLLoc/NLLoc_code/alomax_matrix/alomax_matrix_svd.h
pyNLLoc/NLLoc_code/alomax_matrix/alomax_matrix_svd.o
pyNLLoc/NLLoc_code/geometry/geometry.h
pyNLLoc/NLLoc_code/matrix_statistics/matrix_statistics.c
pyNLLoc/NLLoc_code/matrix_statistics/matrix_statistics.h
pyNLLoc/NLLoc_code/matrix_statistics/matrix_statistics.o
pyNLLoc/NLLoc_code/octtree/geometry.h
pyNLLoc/NLLoc_code/octtree/octtree.c
pyNLLoc/NLLoc_code/octtree/octtree.h
pyNLLoc/NLLoc_code/octtree/octtree.o
pyNLLoc/NLLoc_code/octtree/ran1.h
pyNLLoc/NLLoc_code/ran1/ran1.c
pyNLLoc/NLLoc_code/ran1/ran1.h
pyNLLoc/NLLoc_code/ran1/ran1.o
pyNLLoc/NLLoc_code/vector/vector.c
pyNLLoc/NLLoc_code/vector/vector.h
pyNLLoc/NLLoc_code/vector/vector.o
pyNLLoc-1.0.0.dist-info/DESCRIPTION.rst
pyNLLoc-1.0.0.dist-info/METADATA
pyNLLoc-1.0.0.dist-info/RECORD
pyNLLoc-1.0.0.dist-info/WHEEL
pyNLLoc-1.0.0.dist-info/entry_points.txt
pyNLLoc-1.0.0.dist-info/metadata.json
pyNLLoc-1.0.0.dist-info/top_level.txt
