Metadata-Version: 2.0
Name: pyNLLoc
Version: 1.0.0
Summary: pyNLLoc: Python functions for NonLinLoc and Scat2Angle
Home-page: https://github.com/djpugh/pyNLLoc
Author: David J Pugh
Author-email: djpugh@gmail.com
License: UNKNOWN
Download-URL: https://github.com/djpugh/pyNLLoc/tarball/v1.0.0
Platform: UNKNOWN
Classifier: Development Status :: 5 - Production/Stable
Classifier: Intended Audience :: Science/Research
Classifier: License :: OSI Approved :: GNU General Public License v3 or later (GPLv3+)
Classifier: Natural Language :: English
Classifier: Programming Language :: Python
Classifier: Programming Language :: C++
Classifier: Topic :: Scientific/Engineering
Provides: pyNLLoc
Provides: Scat2Angle
Provides: XYZ2Angle
Requires-Dist: pyqsub (>=1.0.0)
Provides-Extra: Cluster
Requires-Dist: pyqsub (>=1.0.0); extra == 'Cluster'
